asrt_sdk/__init__.py
asrt_sdk/speech_recognizer.py
asrt_sdk/utils.py
asrt_sdk/network/__init__.py
asrt_sdk/network/asrt_pb2.py
asrt_sdk/network/asrt_pb2_grpc.py
asrt_sdk/network/http.py
asrt_sdk/version/__init__.py
asrt_sdk-1.2.0.dist-info/LICENSE
asrt_sdk-1.2.0.dist-info/METADATA
asrt_sdk-1.2.0.dist-info/WHEEL
asrt_sdk-1.2.0.dist-info/top_level.txt
asrt_sdk-1.2.0.dist-info/RECORD
