Metadata-Version: 2.1
Name: asrt-sdk
Version: 1.2.0
Summary: A python sdk for ASRT Speech Recognition Toolkit
Home-page: https://asrt.ailemon.net
Author: ailemon
Author-email: ailemon@ailemon.net
License: GPL v3.0
Download-URL: https://pypi.python.org/pypi/asrt_sdk
Project-URL: Bug Tracker, https://github.com/nl8590687/ASRT_SDK_Python3/issues
Project-URL: Documentation, https://wiki.ailemon.net/docs/asrt-doc/asrt-doc-1dkgqc3871ktt
Project-URL: Source Code, https://github.com/nl8590687/ASRT_SDK_Python3
Platform: UNKNOWN
Classifier: Intended Audience :: Developers
Classifier: Intended Audience :: Education
Classifier: Intended Audience :: Science/Research
Classifier: License :: OSI Approved :: GNU General Public License v3 or later (GPLv3+)
Classifier: Operating System :: OS Independent
Classifier: Programming Language :: Python :: 3
Requires-Python: >=3.0
License-File: LICENSE
Requires-Dist: numpy
Requires-Dist: wave
Requires-Dist: requests
Requires-Dist: grpcio
Requires-Dist: grpcio-tools
Requires-Dist: protobuf
